myepubapp/__init__.py
myepubapp/cli.py
myepubapp/core/__init__.py
myepubapp/core/book.py
myepubapp/core/chapter.py
myepubapp/core/metadata.py
myepubapp/exceptions/__init__.py
myepubapp/exceptions/epub_exceptions.py
myepubapp/generators/__init__.py
myepubapp/generators/content.py
myepubapp/generators/toc.py
myepubapp/utils/__init__.py
myepubapp/utils/epub_validator.py
myepubapp/utils/file_handler.py
myepubapp/utils/logger.py
myepubapp/utils/text_processor.py
myepubapp-1.0.7.dist-info/licenses/LICENSE
myepubapp-1.0.7.dist-info/METADATA
myepubapp-1.0.7.dist-info/WHEEL
myepubapp-1.0.7.dist-info/entry_points.txt
myepubapp-1.0.7.dist-info/top_level.txt
myepubapp-1.0.7.dist-info/RECORD
