Metadata-Version: 2.4
Name: myepubapp
Version: 1.0.7
Summary: A powerful text-to-EPUB conversion tool
Author-email: Sam Weng <eyes1971@gmail.com>
Maintainer-email: Sam Weng <eyes1971@gmail.com>
License-Expression: MIT
Project-URL: Homepage, https://github.com/eyes1971/myepubapp
Project-URL: Repository, https://github.com/eyes1971/myepubapp
Project-URL: Issues, https://github.com/eyes1971/myepubapp/issues
Project-URL: Changelog, https://github.com/eyes1971/myepubapp/blob/main/CHANGELOG.md
Keywords: epub,text-processing,ebook,converter
Classifier: Development Status :: 4 - Beta
Classifier: Intended Audience :: Developers
Classifier: Operating System :: OS Independent
Classifier: Programming Language :: Python :: 3
Classifier: Programming Language :: Python :: 3.8
Classifier: Programming Language :: Python :: 3.9
Classifier: Programming Language :: Python :: 3.10
Classifier: Programming Language :: Python :: 3.11
Classifier: Programming Language :: Python :: 3.12
Classifier: Topic :: Text Processing :: Markup
Classifier: Topic :: Utilities
Requires-Python: >=3.8
License-File: LICENSE
Requires-Dist: ebooklib>=0.18.0
Requires-Dist: beautifulsoup4>=4.12.0
Dynamic: license-file
